{
  "ENTITY-PORTFOLIO": {
    "path": "domain/entity-portfolio.html",
    "title": "Portfolio Entity",
    "status": "active",
    "owner": "portfolio-service"
  },
  "ENTITY-HOLDING": {
    "path": "domain/entity-holding.html",
    "title": "Holding Entity",
    "status": "active",
    "owner": "portfolio-service"
  },
  "ENTITY-TRANSACTION": {
    "path": "domain/entity-transaction.html",
    "title": "Transaction Entity",
    "status": "active",
    "owner": "portfolio-service"
  },
  "BR-PORTFOLIO": {
    "path": "domain/business-rules.html",
    "title": "Portfolio Business Rules",
    "status": "active",
    "owner": "portfolio-service"
  },
  "FR-PORTFOLIO": {
    "path": "domain/functional-requirements.html",
    "title": "Portfolio Functional Requirements",
    "status": "active",
    "owner": "portfolio-service"
  },
  "NFR-PORTFOLIO": {
    "path": "domain/non-functional-requirements.html",
    "title": "Portfolio Non-Functional Requirements",
    "status": "active",
    "owner": "portfolio-service"
  },
  "UC-PORTFOLIO": {
    "path": "domain/use-cases.html",
    "title": "Portfolio Use Case Overview",
    "status": "active",
    "owner": "portfolio-service"
  },
  "UC-BUY": {
    "path": "domain/use-case-buy.html",
    "title": "Place Buy Order",
    "status": "active",
    "owner": "portfolio-service"
  },
  "UC-SELL": {
    "path": "domain/use-case-sell.html",
    "title": "Place Sell Order",
    "status": "active",
    "owner": "portfolio-service"
  },
  "UC-CANCEL": {
    "path": "domain/use-case-cancel.html",
    "title": "Cancel Order",
    "status": "active",
    "owner": "portfolio-service"
  },
  "UC-REVIEW-PORTFOLIO": {
    "path": "domain/use-case-review-portfolio.html",
    "title": "Review Portfolio",
    "status": "active",
    "owner": "portfolio-service"
  },
  "UC-REVIEW-PNL": {
    "path": "domain/use-case-review-pnl.html",
    "title": "Review Total PnL",
    "status": "active",
    "owner": "portfolio-service"
  },
  "REST-GET-PORTFOLIO": {
    "path": "interfaces/rest/api-get-portfolio.html",
    "title": "GET /portfolio",
    "status": "active",
    "owner": "portfolio-service"
  },
  "REST-POST-ORDER": {
    "path": "interfaces/rest/api-post-order.html",
    "title": "POST /portfolio/order",
    "status": "active",
    "owner": "portfolio-service"
  },
  "REST-GET-PNL": {
    "path": "interfaces/rest/api-get-pnl.html",
    "title": "GET /portfolio/pnl",
    "status": "active",
    "owner": "portfolio-service"
  },
  "RERR-PORTFOLIO": {
    "path": "interfaces/rest/error-catalog.html",
    "title": "REST Error Catalog",
    "status": "active",
    "owner": "portfolio-service"
  },
  "REX-MARKET": {
    "path": "messaging/rabbitmq/exchange-market.html",
    "title": "RabbitMQ Exchange: market.exchange",
    "status": "active",
    "owner": "portfolio-service"
  },
  "RQ-PORTFOLIO-PRICE": {
    "path": "messaging/rabbitmq/queue-portfolio-price.html",
    "title": "RabbitMQ Queue: portfolio_service_price_q",
    "status": "active",
    "owner": "portfolio-service"
  },
  "RKEY-PRICE-UPDATE": {
    "path": "messaging/rabbitmq/binding-price-update.html",
    "title": "RabbitMQ Binding: price.updated",
    "status": "active",
    "owner": "portfolio-service"
  },
  "RMQ-CONSUMER-PRICE-UPDATE": {
    "path": "messaging/rabbitmq/consumer-price-update.html",
    "title": "Consumer: PriceUpdateListener",
    "status": "active",
    "owner": "portfolio-service"
  },
  "DBM-SCHEMA-PORTFOLIO": {
    "path": "platform/db-migrations/schema-portfolio.html",
    "title": "Portfolio Schema",
    "status": "active",
    "owner": "portfolio-service"
  },
  "DOC-DOCKER": {
    "path": "platform/deployment/docker.html",
    "title": "Docker Deployment",
    "status": "active",
    "owner": "portfolio-service"
  },
  "DOC-DEPS": {
    "path": "platform/deployment/dependencies.html",
    "title": "Maven Dependencies",
    "status": "active",
    "owner": "portfolio-service"
  },
  "BFLOW-ORDER-EXECUTION": {
    "path": "business-flows/order-execution.html",
    "title": "Order Execution Flow",
    "status": "active",
    "owner": "portfolio-service"
  },
  "BFLOW-PORTFOLIO-REVIEW": {
    "path": "business-flows/portfolio-review.html",
    "title": "Portfolio Review Flow",
    "status": "active",
    "owner": "portfolio-service"
  },
  "BFLOW-PNL-REVIEW": {
    "path": "business-flows/pnl-review.html",
    "title": "PnL Review Flow",
    "status": "active",
    "owner": "portfolio-service"
  },
  "BFLOW-PRICE-UPDATE-INGEST": {
    "path": "business-flows/price-update-ingest.html",
    "title": "Price Update Ingest Flow",
    "status": "active",
    "owner": "portfolio-service"
  },
  "DOC-OVERVIEW": {
    "path": "groups/overview.html",
    "title": "Portfolio Service Overview",
    "status": "active",
    "owner": "portfolio-service"
  },
  "DOC-DOMAIN": {
    "path": "groups/domain.html",
    "title": "Domain Group",
    "status": "active",
    "owner": "portfolio-service"
  },
  "DOC-USE-CASES": {
    "path": "groups/use-cases.html",
    "title": "Use Cases Group",
    "status": "active",
    "owner": "portfolio-service"
  },
  "DOC-BUSINESS-FLOWS": {
    "path": "groups/business-flows.html",
    "title": "Business Flows Group",
    "status": "active",
    "owner": "portfolio-service"
  },
  "DOC-INTERFACES": {
    "path": "groups/interfaces.html",
    "title": "Interfaces Group",
    "status": "active",
    "owner": "portfolio-service"
  },
  "DOC-MESSAGING": {
    "path": "groups/messaging.html",
    "title": "Messaging Group",
    "status": "active",
    "owner": "portfolio-service"
  },
  "DOC-PLATFORM": {
    "path": "groups/platform.html",
    "title": "Platform Group",
    "status": "active",
    "owner": "portfolio-service"
  },
  "DOC-TRACEABILITY": {
    "path": "groups/traceability.html",
    "title": "Traceability Group",
    "status": "active",
    "owner": "portfolio-service"
  },
  "TRACE-PORTFOLIO": {
    "path": "traceability/matrix.html",
    "title": "Portfolio Traceability Matrix",
    "status": "active",
    "owner": "portfolio-service"
  }
}